polyviz/__init__.py
polyviz/chord.py
polyviz/choro.py
polyviz/dataframe.py
polyviz/force.py
polyviz/sankey.py
polyviz/treemap.py
polyviz/utils.py
polyviz/violin.py
polyviz/data/GDP_countries.yaml
polyviz/data/regions.yaml
polyviz-1.0.4.dist-info/LICENSE
polyviz-1.0.4.dist-info/METADATA
polyviz-1.0.4.dist-info/WHEEL
polyviz-1.0.4.dist-info/dependency_links.txt
polyviz-1.0.4.dist-info/top_level.txt
polyviz-1.0.4.dist-info/RECORD
