Metadata-Version: 2.1
Name: polyviz
Version: 1.0.4
Summary: Interface between Brightway2 and D3.js
Home-page: https://github.com/romainsacchi/polyviz
Author: Romain Sacchi <romain.sacchi@psi.ch>
License: BSD 3-Clause License
Classifier: Intended Audience :: End Users/Desktop
Classifier: Intended Audience :: Developers
Classifier: Intended Audience :: Science/Research
Classifier: License :: OSI Approved :: BSD License
Classifier: Operating System :: MacOS :: MacOS X
Classifier: Operating System :: Microsoft :: Windows
Classifier: Operating System :: POSIX
Classifier: Programming Language :: Python
Classifier: Programming Language :: Python :: 3
Classifier: Programming Language :: Python :: 3.5
Classifier: Programming Language :: Python :: 3.6
Classifier: Programming Language :: Python :: 3.7
Classifier: Programming Language :: Python :: 3.8
Classifier: Topic :: Scientific/Engineering :: Information Analysis
Classifier: Topic :: Scientific/Engineering :: Mathematics
Classifier: Topic :: Scientific/Engineering :: Visualization
License-File: LICENSE
Requires-Dist: pandas
Requires-Dist: numpy
Requires-Dist: country-converter
Requires-Dist: pyyaml
